zeroth/__init__.py
zeroth/py.typed
zeroth-1.0.0.dist-info/METADATA
zeroth-1.0.0.dist-info/WHEEL
zeroth-1.0.0.dist-info/licenses/LICENSE
zeroth-1.0.0.dist-info/RECORD
