Metadata-Version: 2.3
Name: zeroth
Version: 1.0.0
Summary: Efficiently get the index-0 element of an iterable.
Project-URL: Bug Tracker, https://github.com/GalacticDynamics/zeroth/issues
Project-URL: Changelog, https://github.com/GalacticDynamics/zeroth/releases
Project-URL: Discussions, https://github.com/GalacticDynamics/zeroth/discussions
Project-URL: Homepage, https://github.com/GalacticDynamics/zeroth
Author-email: Nathaniel Starkman <nstarman@users.noreply.github.com>
License: Copyright 2024 Nathaniel Starkman
License-File: LICENSE
Classifier: Development Status :: 1 - Planning
Classifier: Intended Audience :: Developers
Classifier: Intended Audience :: Science/Research
Classifier: License :: OSI Approved :: MIT License
Classifier: Operating System :: OS Independent
Classifier: Programming Language :: Python
Classifier: Programming Language :: Python :: 3
Classifier: Programming Language :: Python :: 3 :: Only
Classifier: Programming Language :: Python :: 3.8
Classifier: Programming Language :: Python :: 3.9
Classifier: Programming Language :: Python :: 3.10
Classifier: Programming Language :: Python :: 3.11
Classifier: Programming Language :: Python :: 3.12
Classifier: Topic :: Scientific/Engineering
Classifier: Typing :: Typed
Requires-Python: >=3.8
Provides-Extra: dev
Requires-Dist: furo>=2023.08.17; extra == 'dev'
Requires-Dist: myst-parser>=0.13; extra == 'dev'
Requires-Dist: numpy; extra == 'dev'
Requires-Dist: pytest-cov>=3; extra == 'dev'
Requires-Dist: pytest-github-actions-annotate-failures; extra == 'dev'
Requires-Dist: pytest>=6; extra == 'dev'
Requires-Dist: sphinx-autodoc-typehints; extra == 'dev'
Requires-Dist: sphinx-copybutton; extra == 'dev'
Requires-Dist: sphinx>=7.0; extra == 'dev'
Requires-Dist: sybil; extra == 'dev'
Provides-Extra: docs
Requires-Dist: furo>=2023.08.17; extra == 'docs'
Requires-Dist: myst-parser>=0.13; extra == 'docs'
Requires-Dist: sphinx-autodoc-typehints; extra == 'docs'
Requires-Dist: sphinx-copybutton; extra == 'docs'
Requires-Dist: sphinx>=7.0; extra == 'docs'
Provides-Extra: test
Requires-Dist: numpy; extra == 'test'
Requires-Dist: pytest-cov>=3; extra == 'test'
Requires-Dist: pytest-github-actions-annotate-failures; extra == 'test'
Requires-Dist: pytest>=6; extra == 'test'
Requires-Dist: sybil; extra == 'test'
